gedcom5/__init__.py
gedcom5/gedcom.py
gedcom5/parser.py
gedcom5/tag.py
gedcom5-0.2.0.dist-info/LICENSE.txt
gedcom5-0.2.0.dist-info/METADATA
gedcom5-0.2.0.dist-info/WHEEL
gedcom5-0.2.0.dist-info/top_level.txt
gedcom5-0.2.0.dist-info/RECORD
