Metadata-Version: 2.1
Name: gedcom5
Version: 0.2.0
Summary: GEDCOM v5 parser
Author-email: David <c0d3@gpobox.net>
Maintainer-email: David <c0d3@gpobox.net>
License: Copyright © 2023 David <c0d3@gpobox.net>
Project-URL: Homepage, https://github.com/bbc6502/gedcom5
Project-URL: Bug Tracker, https://github.com/bbc6502/gedcom5/issues
Keywords: gedcom
Classifier: Programming Language :: Python :: 3
Classifier: License :: OSI Approved :: MIT License
Classifier: Operating System :: OS Independent
Classifier: Development Status :: 4 - Beta
Requires-Python: >=3.11
License-File: LICENSE.txt
